pyremokit/__init__.py
pyremokit/baseenv.py
pyremokit/baserunner.py
pyremokit/cmdtool/__init__.py
pyremokit/cmdtool/localenv.py
pyremokit/cmdtool/localrunner.py
pyremokit/cmdtool/pexpenv.py
pyremokit/cmdtool/pexprunner.py
pyremokit/cmdtool/pexputils.py
pyremokit/cmdtool/wrmenv.py
pyremokit/cmdtool/wrmrunner.py
pyremokit/utils/__init__.py
pyremokit/utils/aes_gcm.py
pyremokit/utils/pexpssh.py
pyremokit-0.1.3.dist-info/licenses/LICENSE
pyremokit-0.1.3.dist-info/METADATA
pyremokit-0.1.3.dist-info/WHEEL
pyremokit-0.1.3.dist-info/top_level.txt
pyremokit-0.1.3.dist-info/RECORD
