Metadata-Version: 2.4
Name: pyremokit
Version: 0.1.3
Summary: A Python package for remote command execution and automation.
Author-email: lixingxing <lilingxing20@163.com>
Project-URL: Homepage, https://github.com/lilingxing20/pyremokit
Project-URL: Repository, https://github.com/lilingxing20/pyremokit.git
Classifier: Environment :: Console
Classifier: Intended Audience :: Information Technology
Classifier: Intended Audience :: System Administrators
Classifier: Operating System :: POSIX :: Linux
Classifier: Programming Language :: Python
Classifier: Programming Language :: Python :: 3
Classifier: Topic :: System :: Systems Administration
Classifier: Topic :: Software Development :: Libraries :: Python Modules
Requires-Python: >=3.10
License-File: LICENSE
Requires-Dist: requests
Requires-Dist: pycryptodome
Requires-Dist: pexpect>=4.8.0
Requires-Dist: pywinrm>=0.5.0
Dynamic: license-file
